ktypes/__init__.py
ktypes/_abstract_type.py
ktypes/_error.py
ktypes/_kfunc.py
ktypes/_kint.py
ktypes/_kmeta.py
ktypes/_knone.py
ktypes/_kor.py
ktypes/_kstr.py
ktypes/_kuniverse.py
ktypes/_metatype.py
ktypes/_parser.py
ktypes/_token.py
ktypes/core.py
ktypes/rundemo.py
ktypes/runtests.py
ktypes-0.0.1.dist-info/LICENSE
ktypes-0.0.1.dist-info/METADATA
ktypes-0.0.1.dist-info/WHEEL
ktypes-0.0.1.dist-info/top_level.txt
ktypes-0.0.1.dist-info/RECORD
