Metadata-Version: 2.1
Name: ktypes
Version: 0.0.1
Summary: KTypes: Type Theoretic Data Annotations
Home-page: https://github.com/ktvng/ktypes
Author: ktvng
Author-email: k.tang@yale.edu
License: MIT
Project-URL: Source Code, https://github.com/ktvng/ktype
Project-URL: Bug Tracker, https://github.com/ktvng/ktype/issues
Platform: UNKNOWN
Classifier: Programming Language :: Python :: 3
Classifier: License :: OSI Approved :: MIT License
Classifier: Operating System :: OS Independent
Classifier: Development Status :: 2 - Pre-Alpha
Requires-Python: >=3.6
